InsulaWorkflowClient/AscendOpenIDConnect.py
InsulaWorkflowClient/InsulaApiConfig.py
InsulaWorkflowClient/InsulaAuthorizationApiConfig.py
InsulaWorkflowClient/InsulaClient.py
InsulaWorkflowClient/InsulaFederatedIDP.py
InsulaWorkflowClient/InsulaOpenIDConnect.py
InsulaWorkflowClient/InsulaQuery.py
InsulaWorkflowClient/InsulaSearch.py
InsulaWorkflowClient/SingletonMemoryManager.py
InsulaWorkflowClient/WorkflowDataManager.py
InsulaWorkflowClient/__init__.py
InsulaWorkflowClient/delete.py
InsulaWorkflowClient/downloadJob_results.py
InsulaWorkflowClient/files_job_result.py
InsulaWorkflowClient/job_logs.py
InsulaWorkflowClient/job_params.py
InsulaWorkflowClient/job_runner.py
InsulaWorkflowClient/job_status.py
InsulaWorkflowClient/logger.py
InsulaWorkflowClient/placeholders.py
InsulaWorkflowClient/results_manager.py
InsulaWorkflowClient/s3.py
InsulaWorkflowClient/step_result.py
InsulaWorkflowClient/utils.py
InsulaWorkflowClient/workflow.py
InsulaWorkflowClient/workflow_manager.py
InsulaWorkflowClient/workflow_step.py
InsulaWorkflowClient/workflow_step_runner.py
insulaworkflowclient-0.8.9.dist-info/METADATA
insulaworkflowclient-0.8.9.dist-info/WHEEL
insulaworkflowclient-0.8.9.dist-info/entry_points.txt
insulaworkflowclient-0.8.9.dist-info/RECORD
