Metadata-Version: 2.4
Name: InsulaWorkflowClient
Version: 0.8.9
Summary: Insula Workflow CLient
Author-email: Roberto Di Rienzo <roberto.dirienzo@codelithic.com>
Maintainer-email: Roberto Di Rienzo <roberto.dirienzo@cgi.com>
Keywords: Italia,cgi,client,insula
Classifier: Development Status :: 4 - Beta
Classifier: Programming Language :: Python
Requires-Python: >=3.9
Requires-Dist: boto3
Requires-Dist: lxml
Requires-Dist: pydantic
Requires-Dist: python-jose
Requires-Dist: pyyaml
Requires-Dist: requests
Requires-Dist: snakenest==0.3.0
Requires-Dist: urllib3
